setup.py
cqh_image/__init__.py
cqh_image/__main__.py
cqh_image/handler_image.py
cqh_image/run.py
cqh_image.egg-info/PKG-INFO
cqh_image.egg-info/SOURCES.txt
cqh_image.egg-info/dependency_links.txt
cqh_image.egg-info/entry_points.txt
cqh_image.egg-info/requires.txt
cqh_image.egg-info/top_level.txt